Workbook

Sheet Resumen
A1: Mosaicca · Proyección de demanda, noviembre y diciembre de 2026
A2: Estimación por escenarios con supuestos editables. No hay historial de ventas en el proyecto: calibra la hoja Supuestos con tus pedidos reales antes de producir.
A4: Ingresos proyectados (MXN) | B4: Conservador | C4: Base | D4: Optimista
A5: Noviembre | B5: =Demanda!C16 -> 9146.4348 | C5: =Demanda!D16 -> 22265.512 | D5: =Demanda!E16 -> 51988.248
A6: Diciembre | B6: =Demanda!C31 -> 12861.673 | C6: =Demanda!D31 -> 30216.706 | D6: =Demanda!E31 -> 66675.086
A7: Total noviembre + diciembre | B7: =B5+B6 -> 22008.108 | C7: =C5+C6 -> 52482.218 | D7: =D5+D6 -> 118663.33
A8: Pedidos totales | B8: =Demanda!C36 -> 68.775336 | C8: =Demanda!D36 -> 138.1111 | D8: =Demanda!E36 -> 263.6963
A9: Inversión en anuncios | B9: =Demanda!C37 -> 8000 | C9: =Demanda!D37 -> 12000 | D9: =Demanda!E37 -> 18000
A10: ROAS de los anuncios (todo el periodo) | B10: =IFERROR((Demanda!C14+Demanda!C29)/B9,0) -> 0.22301344 | C10: =IFERROR((Demanda!D14+Demanda!D29)/C9,0) -> 0.77111816 | D10: =IFERROR((Demanda!E14+Demanda!E29)/D9,0) -> 2.1684075
A11: Ingresos que dependen de anuncios | B11: =Demanda!C38 -> 0.081065921 | C11: =Demanda!D38 -> 0.1763153 | D11: =Demanda!E38 -> 0.32892497
A12: Ingreso por habitante de México | B12: =Mercado!B26 -> 0.00016811463 | C12: =Mercado!C26 -> 0.00040089902 | D12: =Mercado!D26 -> 0.00090644063
A14: Qué producir (escenario base + colchón)
A15: Producto | B15: Ingresos nov + dic | C15: Unidades base | D15: Producir | E15: Tipo
A16: =Producción!A5 -> Fichas de lotería sueltas | B16: =Producción!F5 -> 1872.4698 | C16: =Producción!M5 -> 374.49396 | D16: =Producción!N5 -> 431 | E16: =Producción!C5 -> Stock
A17: =Producción!A6 -> Paquete de 25 fichas | B17: =Producción!F6 -> 5688.876 | C17: =Producción!M6 -> 81.269657 | D17: =Producción!N6 -> 94 | E17: =Producción!C6 -> Stock
A18: =Producción!A7 -> Paquete de 50 fichas | B18: =Producción!F7 -> 5143.6751 | C18: =Producción!M7 -> 38.101297 | D18: =Producción!N7 -> 44 | E18: =Producción!C7 -> Stock
A19: =Producción!A8 -> Paquete de 100 fichas | B19: =Producción!F8 -> 4433.0736 | C19: =Producción!M8 -> 15.832406 | D19: =Producción!N8 -> 19 | E19: =Producción!C8 -> Stock
A20: =Producción!A9 -> Tazas personalizadas | B20: =Producción!F9 -> 4669.9408 | C20: =Producción!M9 -> 23.58556 | D20: =Producción!N9 -> 28 | E20: =Producción!C9 -> Bajo pedido
A21: =Producción!A10 -> Vasos y termos personalizados | B21: =Producción!F10 -> 5760.3426 | C21: =Producción!M10 -> 11.590226 | D21: =Producción!N10 -> 14 | E21: =Producción!C10 -> Bajo pedido
A22: =Producción!A11 -> Agendas | B22: =Producción!F11 -> 5286.6083 | C22: =Producción!M11 -> 13.316394 | D22: =Producción!N11 -> 16 | E22: =Producción!C11 -> Bajo pedido
A23: =Producción!A12 -> Libretas | B23: =Producción!F12 -> 2489.1373 | C23: =Producción!M12 -> 9.9565491 | D23: =Producción!N12 -> 12 | E23: =Producción!C12 -> Bajo pedido
A24: =Producción!A13 -> Sellos (madera, autoentintables y cera) | B24: =Producción!F13 -> 4218.6739 | C24: =Producción!M13 -> 9.9497026 | D24: =Producción!N13 -> 12 | E24: =Producción!C13 -> Bajo pedido
A25: =Producción!A14 -> Impresión 3D y otros personalizados | B25: =Producción!F14 -> 1635.6026 | C25: =Producción!M14 -> 2.7260044 | D25: =Producción!N14 -> 4 | E25: =Producción!C14 -> Bajo pedido
A26: =Producción!A15 -> Mini CD con NFC | B26: =Producción!F15 -> 3887.8728 | C26: =Producción!M15 -> 21.015528 | D26: =Producción!N15 -> 25 | E26: =Producción!C15 -> Stock
A27: =Producción!A16 -> Colección Pride | B27: =Producción!F16 -> 1327.2689 | C27: =Producción!M16 -> 4.9340852 | D27: =Producción!N16 -> 6 | E27: =Producción!C16 -> Stock
A28: =Producción!A17 -> Kits y regalos de temporada (Navidad) | B28: =Producción!F17 -> 6068.6763 | C28: =Producción!M17 -> 6.7429737 | D28: =Producción!N17 -> 8 | E28: =Producción!C17 -> Bajo pedido
A29: Total | B29: =SUM(B16:B28) -> 52482.218
A30: Piezas de ficha a imprimir (base + colchón) | D30: =Producción!N23 -> 6779
A32: Cómo leer esto
A33: 1. Los tres escenarios mueven la inversión, el CPM, el CTR, la conversión, el ticket y los pedidos orgánicos. Ninguno es un pronóstico garantizado.
A34: 2. El supuesto que más pesa son tus pedidos orgánicos por semana (hoja Supuestos, fila 11, en amarillo). Con tu dato real, la proyección pasa de estimación a cálculo.
A35: 3. Con estos supuestos, los anuncios por sí solos recuperan menos de lo que cuestan en la primera compra (ROAS menor a 1). Su valor está en construir audiencia para retargeting y para los pedidos orgánicos.
A36: 4. Las fichas de $5 no sostienen la inversión: el modelo las trata como gancho. Los paquetes, los personalizados y los kits son los que mueven el ingreso.
A37: 5. Los kits de temporada y la impresión 3D se cotizan en la tienda; sus precios de $900 y $600 son supuestos para que confirmes.
A38: 6. Faltan datos para calcular utilidad: costo de producción, capacidad de impresión y tiempos de entrega. Con ellos se agrega margen y fecha límite de pedidos.

Sheet Supuestos
A1: Supuestos del modelo · Mosaicca · noviembre y diciembre de 2026
A2: Azul = dato que tú editas. Amarillo = el que más mueve el resultado: cámbialo por tu dato real. Todo lo demás se recalcula solo.
A4: Supuesto (por escenario) | B4: Unidad | C4: Conservador | D4: Base | E4: Optimista | F4: Fuente o nota
A5: Inversión en anuncios · noviembre | B5: MXN | C5: 4000 | D5: 6000 | E5: 9000 | F5: Base = el ejemplo de la campaña de Facebook ($200 al día). Decisión tuya.
A6: Inversión en anuncios · diciembre | B6: MXN | C6: 4000 | D6: 6000 | E6: 9000 | F6: Igual que arriba.
A7: CPM (costo por mil impresiones) | B7: MXN | C7: 110 | D7: 85 | E7: 70 | F7: Supuesto del modelo. Reemplázalo con el CPM real de tu Administrador de anuncios.
A8: CTR de enlace (clics ÷ impresiones) | B8: % | C8: 0.008 | D8: 0.012 | E8: 0.016 | F8: Supuesto del modelo. Reemplázalo con tu CTR real.
A9: Clic → pedido (tienda web y WhatsApp) | B9: % | C9: 0.01 | D9: 0.015 | E9: 0.022 | F9: Supuesto del modelo para tráfico frío de una tienda pequeña.
A10: Ticket promedio por pedido | B10: MXN | C10: 320 | D10: 380 | E10: 450 | F10: Supuesto. Los paquetes ($70 a $280) y los personalizados ($150 a $700) fijan el ticket.
A11: Pedidos orgánicos por semana (sin anuncios) | B11: pedidos | C11: 5 | D11: 9 | E11: 14 | F11: NO TENGO TUS VENTAS. Pon aquí tus pedidos semanales reales de las últimas 4 semanas (WhatsApp, Instagram, tienda).
A13: Factores de temporada (iguales en los 3 escenarios) | B13: Unidad | C13: Noviembre | D13: Diciembre | F13: Fuente o nota
A14: Factor CPM (competencia por Buen Fin y Navidad) | B14: x | C14: 1.15 | D14: 1.25 | F14: Supuesto: los anuncios se encarecen cuando compite todo el comercio.
A15: Factor de conversión | B15: x | C15: 1.1 | D15: 1.2 | F15: Supuesto: más intención de compra en Buen Fin y aguinaldo.
A16: Factor de pedidos orgánicos | B16: x | C16: 1.2 | D16: 1.7 | F16: Supuesto: la lotería y los regalos se mueven sobre todo en diciembre (posadas, aguinaldo).
A17: Semanas del mes | B17: semanas | C17: 4.3 | D17: 4.4 | F17: Días del mes ÷ 7.
A19: Colchón de producción sobre la demanda base | B19: % | C19: 0.15 | F19: Supuesto. Cubre picos y mermas. Súbelo si tu tiempo de entrega es largo.
A21: Mezcla de ingresos por producto
A22: Los pesos no tienen que sumar 100: el modelo los convierte en porcentaje. Los precios salen de la tienda (promedios ponderados por grupo).
A23: Producto | B23: Precio unit. (MXN) | C23: Peso noviembre | D23: Peso diciembre | E23: Tipo de producción | F23: Nota | G23: Piezas de ficha por unidad
A24: Fichas de lotería sueltas | B24: 5 | C24: 4 | D24: 3 | E24: Stock | F24: Precio de la tienda. Pieza más barata: sirve de gancho. | G24: 1
A25: Paquete de 25 fichas | B25: 70 | C25: 11 | D25: 10 | E25: Stock | F25: Precio de la tienda. | G25: 25
A26: Paquete de 50 fichas | B26: 135 | C26: 10 | D26: 9 | E26: Stock | F26: Precio de la tienda. | G26: 50
A27: Paquete de 100 fichas | B27: 280 | C27: 7 | D27: 9 | E27: Stock | F27: Precio de la tienda. Sube en diciembre: juego completo para posadas. | G27: 100
A28: Tazas personalizadas | B28: 198 | C28: 8 | D28: 9 | E28: Bajo pedido | F28: Promedio de las 2 tazas ($150 y $245). | G28: 0
A29: Vasos y termos personalizados | B29: 497 | C29: 10 | D29: 11 | E29: Bajo pedido | F29: Promedio ponderado de 7 vasos ($360 a $450) y 3 termos ($600 a $700). | G29: 0
A30: Agendas | B30: 397 | C30: 8 | D30: 11 | E30: Bajo pedido | F30: Promedio de 6 modelos ($180 a $650). Pico de agendas 2027 en diciembre. | G30: 0
A31: Libretas | B31: 250 | C31: 4 | D31: 5 | E31: Bajo pedido | F31: Promedio de 6 modelos ($100 a $450). | G31: 0
A32: Sellos (madera, autoentintables y cera) | B32: 424 | C32: 10 | D32: 6 | E32: Bajo pedido | F32: Promedio ponderado de 10 modelos ($196 a $879). | G32: 0
A33: Impresión 3D y otros personalizados | B33: 600 | C33: 3 | D33: 3 | E33: Bajo pedido | F33: A cotizar en la tienda. $600 es un supuesto tuyo para confirmar. | G33: 0
A34: Mini CD con NFC | B34: 185 | C34: 6 | D34: 8 | E34: Stock | F34: Precio de promoción de la tienda (regular $219). | G34: 0
A35: Colección Pride | B35: 269 | C35: 3 | D35: 2 | E35: Stock | F35: Promedio ponderado de 11 productos con precio ($15 a $450). Fuera de temporada (jun a ago). | G35: 0
A36: Kits y regalos de temporada (Navidad) | B36: 900 | C36: 10 | D36: 12 | E36: Bajo pedido | F36: A cotizar en la tienda. $900 es un supuesto tuyo para confirmar. | G36: 0
A37: Suma de pesos | C37: =SUM(C24:C36) -> 94 | D37: =SUM(D24:D36) -> 98

Sheet Mercado
A1: Mercado y consumo per cápita en México
A2: Contexto de arriba hacia abajo. Sirve para juzgar si la proyección de la hoja Demanda es razonable frente al tamaño del mercado.
A4: Dato | B4: Valor | C4: Unidad | E4: Fuente o nota
A5: Población de México (15 oct 2025) | B5: 130911314 | C5: personas | E5: INEGI, Encuesta Intercensal 2025 (vía Uno TV y Xataka México).
A6: Personas por hogar | B6: 3.4 | C6: personas | E6: Supuesto del modelo (INEGI reporta hogares más pequeños). Verifica el dato de INEGI.
A7: Hogares en México | B7: =B5/B6 -> 38503328 | C7: hogares | E7: Cálculo.
A8: Gasto promedio en regalos de Navidad por hogar | B8: 6359 | C8: MXN | E8: Kantar 2025, citado por Milenio y El CEO (otras encuestas dan desde $4,022; ver hoja Fuentes).
A9: Mercado de regalos de Navidad | B9: =B7*B8 -> 2.4484266e+11 | C9: MXN | E9: Cálculo: hogares × gasto por hogar.
A10: Parte que se compra en línea | B10: 0.3 | C10: % | E10: Supuesto dentro del rango de 21% a 55% que reporta Deloitte (vía Marketing4eCommerce).
A11: Mercado de regalos en línea | B11: =B9*B10 -> 7.3452798e+10 | C11: MXN | E11: Cálculo.
A12: Parte que va a personalizados, coleccionables y papelería | B12: 0.015 | C12: % | E12: Supuesto del modelo. No existe una cifra pública para este nicho; cámbiala si tienes una mejor.
A13: Mercado direccionable en línea (SAM) | B13: =B11*B12 -> 1.101792e+09 | C13: MXN | E13: Cálculo.
A15: Referencias del comercio en línea (no entran al cálculo)
A16: Ventas del comercio electrónico en México, 2025 | B16: 941000000000 | C16: MXN | E16: AMVO (cifra reportada por prensa; no encontré el estudio original).
A17: Compradores digitales en México, 2025 | B17: 77200000 | C17: personas | E17: AMVO (vía prensa).
A18: Gasto en línea por comprador digital al año | B18: =B16/B17 -> 12189.119 | C18: MXN | E18: Cálculo.
A19: Derrama económica del Buen Fin 2025 | B19: 219000000000 | C19: MXN | E19: Secretaría de Economía (+26.6% frente a 2024).
A20: Ventas en línea del Buen Fin 2025 | B20: 45900000000 | C20: MXN | E20: AMVO (21% de la derrama).
A21: Ticket promedio del Hot Sale 2025 | B21: 1100 | C21: MXN | E21: AMVO (vía Milenio y Expansión).
A23: Contraste con la proyección (hoja Demanda)
A24: Indicador | B24: Conservador | C24: Base | D24: Optimista
A25: Ingresos nov + dic proyectados (MXN) | B25: =Demanda!C35 -> 22008.108 | C25: =Demanda!D35 -> 52482.218 | D25: =Demanda!E35 -> 118663.33
A26: Ingreso por habitante de México (MXN) | B26: =B25/$B$5 -> 0.00016811463 | C26: =C25/$B$5 -> 0.00040089902 | D26: =D25/$B$5 -> 0.00090644063
A27: Cuota implícita del mercado direccionable (SAM) | B27: =B25/$B$13 -> 1.997483e-05 | C27: =C25/$B$13 -> 4.7633509e-05 | D27: =D25/$B$13 -> 0.00010770031
A28: Pesos vendidos por cada $1,000,000 del SAM | B28: =B27*1000000 -> 19.97483 | C28: =C27*1000000 -> 47.633509 | D28: =D27*1000000 -> 107.70031
A30: Lectura: una cuota por debajo de 0.01% del SAM es realista para una marca pequeña que vende en línea con anuncios locales y nacionales. Si te sale mucho más alta, revisa tus supuestos de pedidos.

Sheet Demanda
A1: Demanda e ingresos proyectados · de abajo hacia arriba
A2: Anuncios: inversión ÷ CPM → impresiones → clics → pedidos. Más los pedidos que ya llegan sin anuncios, ajustados por temporada.
A4: Concepto | B4: Unidad | C4: Conservador | D4: Base | E4: Optimista
A5: NOVIEMBRE
A6: Inversión en anuncios | B6: MXN | C6: =Supuestos!C5 -> 4000 | D6: =Supuestos!D5 -> 6000 | E6: =Supuestos!E5 -> 9000
A7: CPM efectivo (con factor de temporada) | B7: MXN | C7: =Supuestos!C7*Supuestos!$C$14 -> 126.5 | D7: =Supuestos!D7*Supuestos!$C$14 -> 97.75 | E7: =Supuestos!E7*Supuestos!$C$14 -> 80.5
A8: Impresiones | B8: impr. | C8: =C6/C7*1000 -> 31620.553 | D8: =D6/D7*1000 -> 61381.074 | E8: =E6/E7*1000 -> 111801.24
A9: Clics al sitio o a WhatsApp | B9: clics | C9: =C8*Supuestos!C8 -> 252.96443 | D9: =D8*Supuestos!D8 -> 736.57289 | E9: =E8*Supuestos!E8 -> 1788.8199
A10: Conversión efectiva (clic → pedido) | B10: % | C10: =Supuestos!C9*Supuestos!$C$15 -> 0.011 | D10: =Supuestos!D9*Supuestos!$C$15 -> 0.0165 | E10: =Supuestos!E9*Supuestos!$C$15 -> 0.0242
A11: Pedidos por anuncios | B11: pedidos | C11: =C9*C10 -> 2.7826087 | D11: =D9*D10 -> 12.153453 | E11: =E9*E10 -> 43.289441
A12: Pedidos orgánicos (sin anuncios) | B12: pedidos | C12: =Supuestos!C11*Supuestos!$C$17*Supuestos!$C$16 -> 25.8 | D12: =Supuestos!D11*Supuestos!$C$17*Supuestos!$C$16 -> 46.44 | E12: =Supuestos!E11*Supuestos!$C$17*Supuestos!$C$16 -> 72.24
A13: Pedidos totales | B13: pedidos | C13: =C11+C12 -> 28.582609 | D13: =D11+D12 -> 58.593453 | E13: =E11+E12 -> 115.52944
A14: Ingresos por anuncios | B14: MXN | C14: =C11*Supuestos!C10 -> 890.43478 | D14: =D11*Supuestos!D10 -> 4618.312 | E14: =E11*Supuestos!E10 -> 19480.248
A15: Ingresos orgánicos | B15: MXN | C15: =C12*Supuestos!C10 -> 8256 | D15: =D12*Supuestos!D10 -> 17647.2 | E15: =E12*Supuestos!E10 -> 32508
A16: INGRESOS TOTALES DEL MES | B16: MXN | C16: =C14+C15 -> 9146.4348 | D16: =D14+D15 -> 22265.512 | E16: =E14+E15 -> 51988.248
A17: ROAS de anuncios (ingreso ÷ inversión) | B17: x | C17: =IFERROR(C14/C6,0) -> 0.2226087 | D17: =IFERROR(D14/D6,0) -> 0.76971867 | E17: =IFERROR(E14/E6,0) -> 2.164472
A20: DICIEMBRE
A21: Inversión en anuncios | B21: MXN | C21: =Supuestos!C6 -> 4000 | D21: =Supuestos!D6 -> 6000 | E21: =Supuestos!E6 -> 9000
A22: CPM efectivo (con factor de temporada) | B22: MXN | C22: =Supuestos!C7*Supuestos!$D$14 -> 137.5 | D22: =Supuestos!D7*Supuestos!$D$14 -> 106.25 | E22: =Supuestos!E7*Supuestos!$D$14 -> 87.5
A23: Impresiones | B23: impr. | C23: =C21/C22*1000 -> 29090.909 | D23: =D21/D22*1000 -> 56470.588 | E23: =E21/E22*1000 -> 102857.14
A24: Clics al sitio o a WhatsApp | B24: clics | C24: =C23*Supuestos!C8 -> 232.72727 | D24: =D23*Supuestos!D8 -> 677.64706 | E24: =E23*Supuestos!E8 -> 1645.7143
A25: Conversión efectiva (clic → pedido) | B25: % | C25: =Supuestos!C9*Supuestos!$D$15 -> 0.012 | D25: =Supuestos!D9*Supuestos!$D$15 -> 0.018 | E25: =Supuestos!E9*Supuestos!$D$15 -> 0.0264
A26: Pedidos por anuncios | B26: pedidos | C26: =C24*C25 -> 2.7927273 | D26: =D24*D25 -> 12.197647 | E26: =E24*E25 -> 43.446857
A27: Pedidos orgánicos (sin anuncios) | B27: pedidos | C27: =Supuestos!C11*Supuestos!$D$17*Supuestos!$D$16 -> 37.4 | D27: =Supuestos!D11*Supuestos!$D$17*Supuestos!$D$16 -> 67.32 | E27: =Supuestos!E11*Supuestos!$D$17*Supuestos!$D$16 -> 104.72
A28: Pedidos totales | B28: pedidos | C28: =C26+C27 -> 40.192727 | D28: =D26+D27 -> 79.517647 | E28: =E26+E27 -> 148.16686
A29: Ingresos por anuncios | B29: MXN | C29: =C26*Supuestos!C10 -> 893.67273 | D29: =D26*Supuestos!D10 -> 4635.1059 | E29: =E26*Supuestos!E10 -> 19551.086
A30: Ingresos orgánicos | B30: MXN | C30: =C27*Supuestos!C10 -> 11968 | D30: =D27*Supuestos!D10 -> 25581.6 | E30: =E27*Supuestos!E10 -> 47124
A31: INGRESOS TOTALES DEL MES | B31: MXN | C31: =C29+C30 -> 12861.673 | D31: =D29+D30 -> 30216.706 | E31: =E29+E30 -> 66675.086
A32: ROAS de anuncios (ingreso ÷ inversión) | B32: x | C32: =IFERROR(C29/C21,0) -> 0.22341818 | D32: =IFERROR(D29/D21,0) -> 0.77251765 | E32: =IFERROR(E29/E21,0) -> 2.1723429
A34: TOTAL
A35: Ingresos nov + dic | B35: MXN | C35: =C16+C31 -> 22008.108 | D35: =D16+D31 -> 52482.218 | E35: =E16+E31 -> 118663.33
A36: Pedidos totales nov + dic | B36: pedidos | C36: =C13+C28 -> 68.775336 | D36: =D13+D28 -> 138.1111 | E36: =E13+E28 -> 263.6963
A37: Inversión total en anuncios | B37: MXN | C37: =C6+C21 -> 8000 | D37: =D6+D21 -> 12000 | E37: =E6+E21 -> 18000
A38: Porcentaje de ingresos que depende de anuncios | B38: % | C38: =IFERROR((C14+C29)/C35,0) -> 0.081065921 | D38: =IFERROR((D14+D29)/D35,0) -> 0.1763153 | E38: =IFERROR((E14+E29)/E35,0) -> 0.32892497
A40: Los ingresos son ventas brutas con IVA incluido si tus precios lo incluyen; no descuentan comisiones, envíos ni costos de producción.

Sheet Producción
A1: Ingresos y producción por producto
A2: Unidades = ingresos del mes × peso del producto ÷ precio. «Producir» = demanda base de nov + dic más el colchón. Para productos bajo pedido, es el material a tener listo.
A4: Producto | B4: Precio (MXN) | C4: Tipo | D4: Ingresos nov (base) | E4: Ingresos dic (base) | F4: Ingresos nov + dic (base) | G4: Unid. nov · conserv. | H4: Unid. nov · base | I4: Unid. nov · optim. | J4: Unid. dic · conserv. | K4: Unid. dic · base | L4: Unid. dic · optim. | M4: Total unid. (base) | N4: Producir (base + colchón) | O4: Tope si se cumple el escenario optimista
A5: =Supuestos!A24 -> Fichas de lotería sueltas | B5: =Supuestos!B24 -> 5 | C5: =Supuestos!E24 -> Stock | D5: =Demanda!$D$16*Supuestos!$C24/Supuestos!$C$37 -> 947.4686 | E5: =Demanda!$D$31*Supuestos!$D24/Supuestos!$D$37 -> 925.0012 | F5: =D5+E5 -> 1872.4698 | G5: =Demanda!C$16*Supuestos!$C24/Supuestos!$C$37/B5 -> 77.841998 | H5: =Demanda!D$16*Supuestos!$C24/Supuestos!$C$37/B5 -> 189.49372 | I5: =Demanda!E$16*Supuestos!$C24/Supuestos!$C$37/B5 -> 442.45318 | J5: =Demanda!C$31*Supuestos!$D24/Supuestos!$D$37/B5 -> 78.744935 | K5: =Demanda!D$31*Supuestos!$D24/Supuestos!$D$37/B5 -> 185.00024 | L5: =Demanda!E$31*Supuestos!$D24/Supuestos!$D$37/B5 -> 408.21481 | M5: =H5+K5 -> 374.49396 | N5: =ROUNDUP(M5*(1+Supuestos!$C$19),0) -> 431 | O5: =ROUNDUP((I5+L5)*(1+Supuestos!$C$19),0) -> 979
A6: =Supuestos!A25 -> Paquete de 25 fichas | B6: =Supuestos!B25 -> 70 | C6: =Supuestos!E25 -> Stock | D6: =Demanda!$D$16*Supuestos!$C25/Supuestos!$C$37 -> 2605.5386 | E6: =Demanda!$D$31*Supuestos!$D25/Supuestos!$D$37 -> 3083.3373 | F6: =D6+E6 -> 5688.876 | G6: =Demanda!C$16*Supuestos!$C25/Supuestos!$C$37/B6 -> 15.290392 | H6: =Demanda!D$16*Supuestos!$C25/Supuestos!$C$37/B6 -> 37.221981 | I6: =Demanda!E$16*Supuestos!$C25/Supuestos!$C$37/B6 -> 86.910446 | J6: =Demanda!C$31*Supuestos!$D25/Supuestos!$D$37/B6 -> 18.748794 | K6: =Demanda!D$31*Supuestos!$D25/Supuestos!$D$37/B6 -> 44.047676 | L6: =Demanda!E$31*Supuestos!$D25/Supuestos!$D$37/B6 -> 97.194002 | M6: =H6+K6 -> 81.269657 | N6: =ROUNDUP(M6*(1+Supuestos!$C$19),0) -> 94 | O6: =ROUNDUP((I6+L6)*(1+Supuestos!$C$19),0) -> 212
A7: =Supuestos!A26 -> Paquete de 50 fichas | B7: =Supuestos!B26 -> 135 | C7: =Supuestos!E26 -> Stock | D7: =Demanda!$D$16*Supuestos!$C26/Supuestos!$C$37 -> 2368.6715 | E7: =Demanda!$D$31*Supuestos!$D26/Supuestos!$D$37 -> 2775.0036 | F7: =D7+E7 -> 5143.6751 | G7: =Demanda!C$16*Supuestos!$C26/Supuestos!$C$37/B7 -> 7.2075924 | H7: =Demanda!D$16*Supuestos!$C26/Supuestos!$C$37/B7 -> 17.545715 | I7: =Demanda!E$16*Supuestos!$C26/Supuestos!$C$37/B7 -> 40.967887 | J7: =Demanda!C$31*Supuestos!$D26/Supuestos!$D$37/B7 -> 8.7494372 | K7: =Demanda!D$31*Supuestos!$D26/Supuestos!$D$37/B7 -> 20.555582 | L7: =Demanda!E$31*Supuestos!$D26/Supuestos!$D$37/B7 -> 45.357201 | M7: =H7+K7 -> 38.101297 | N7: =ROUNDUP(M7*(1+Supuestos!$C$19),0) -> 44 | O7: =ROUNDUP((I7+L7)*(1+Supuestos!$C$19),0) -> 100
A8: =Supuestos!A27 -> Paquete de 100 fichas | B8: =Supuestos!B27 -> 280 | C8: =Supuestos!E27 -> Stock | D8: =Demanda!$D$16*Supuestos!$C27/Supuestos!$C$37 -> 1658.07 | E8: =Demanda!$D$31*Supuestos!$D27/Supuestos!$D$37 -> 2775.0036 | F8: =D8+E8 -> 4433.0736 | G8: =Demanda!C$16*Supuestos!$C27/Supuestos!$C$37/B8 -> 2.4325624 | H8: =Demanda!D$16*Supuestos!$C27/Supuestos!$C$37/B8 -> 5.9216787 | I8: =Demanda!E$16*Supuestos!$C27/Supuestos!$C$37/B8 -> 13.826662 | J8: =Demanda!C$31*Supuestos!$D27/Supuestos!$D$37/B8 -> 4.2184787 | K8: =Demanda!D$31*Supuestos!$D27/Supuestos!$D$37/B8 -> 9.9107271 | L8: =Demanda!E$31*Supuestos!$D27/Supuestos!$D$37/B8 -> 21.868651 | M8: =H8+K8 -> 15.832406 | N8: =ROUNDUP(M8*(1+Supuestos!$C$19),0) -> 19 | O8: =ROUNDUP((I8+L8)*(1+Supuestos!$C$19),0) -> 42
A9: =Supuestos!A28 -> Tazas personalizadas | B9: =Supuestos!B28 -> 198 | C9: =Supuestos!E28 -> Bajo pedido | D9: =Demanda!$D$16*Supuestos!$C28/Supuestos!$C$37 -> 1894.9372 | E9: =Demanda!$D$31*Supuestos!$D28/Supuestos!$D$37 -> 2775.0036 | F9: =D9+E9 -> 4669.9408 | G9: =Demanda!C$16*Supuestos!$C28/Supuestos!$C$37/B9 -> 3.931414 | H9: =Demanda!D$16*Supuestos!$C28/Supuestos!$C$37/B9 -> 9.5703899 | I9: =Demanda!E$16*Supuestos!$C28/Supuestos!$C$37/B9 -> 22.34612 | J9: =Demanda!C$31*Supuestos!$D28/Supuestos!$D$37/B9 -> 5.9655254 | K9: =Demanda!D$31*Supuestos!$D28/Supuestos!$D$37/B9 -> 14.01517 | L9: =Demanda!E$31*Supuestos!$D28/Supuestos!$D$37/B9 -> 30.925364 | M9: =H9+K9 -> 23.58556 | N9: =ROUNDUP(M9*(1+Supuestos!$C$19),0) -> 28 | O9: =ROUNDUP((I9+L9)*(1+Supuestos!$C$19),0) -> 62
A10: =Supuestos!A29 -> Vasos y termos personalizados | B10: =Supuestos!B29 -> 497 | C10: =Supuestos!E29 -> Bajo pedido | D10: =Demanda!$D$16*Supuestos!$C29/Supuestos!$C$37 -> 2368.6715 | E10: =Demanda!$D$31*Supuestos!$D29/Supuestos!$D$37 -> 3391.6711 | F10: =D10+E10 -> 5760.3426 | G10: =Demanda!C$16*Supuestos!$C29/Supuestos!$C$37/B10 -> 1.9577967 | H10: =Demanda!D$16*Supuestos!$C29/Supuestos!$C$37/B10 -> 4.7659386 | I10: =Demanda!E$16*Supuestos!$C29/Supuestos!$C$37/B10 -> 11.128098 | J10: =Demanda!C$31*Supuestos!$D29/Supuestos!$D$37/B10 -> 2.9047427 | K10: =Demanda!D$31*Supuestos!$D29/Supuestos!$D$37/B10 -> 6.8242879 | L10: =Demanda!E$31*Supuestos!$D29/Supuestos!$D$37/B10 -> 15.058226 | M10: =H10+K10 -> 11.590226 | N10: =ROUNDUP(M10*(1+Supuestos!$C$19),0) -> 14 | O10: =ROUNDUP((I10+L10)*(1+Supuestos!$C$19),0) -> 31
A11: =Supuestos!A30 -> Agendas | B11: =Supuestos!B30 -> 397 | C11: =Supuestos!E30 -> Bajo pedido | D11: =Demanda!$D$16*Supuestos!$C30/Supuestos!$C$37 -> 1894.9372 | E11: =Demanda!$D$31*Supuestos!$D30/Supuestos!$D$37 -> 3391.6711 | F11: =D11+E11 -> 5286.6083 | G11: =Demanda!C$16*Supuestos!$C30/Supuestos!$C$37/B11 -> 1.9607556 | H11: =Demanda!D$16*Supuestos!$C30/Supuestos!$C$37/B11 -> 4.7731415 | I11: =Demanda!E$16*Supuestos!$C30/Supuestos!$C$37/B11 -> 11.144916 | J11: =Demanda!C$31*Supuestos!$D30/Supuestos!$D$37/B11 -> 3.636416 | K11: =Demanda!D$31*Supuestos!$D30/Supuestos!$D$37/B11 -> 8.5432521 | L11: =Demanda!E$31*Supuestos!$D30/Supuestos!$D$37/B11 -> 18.85123 | M11: =H11+K11 -> 13.316394 | N11: =ROUNDUP(M11*(1+Supuestos!$C$19),0) -> 16 | O11: =ROUNDUP((I11+L11)*(1+Supuestos!$C$19),0) -> 35
A12: =Supuestos!A31 -> Libretas | B12: =Supuestos!B31 -> 250 | C12: =Supuestos!E31 -> Bajo pedido | D12: =Demanda!$D$16*Supuestos!$C31/Supuestos!$C$37 -> 947.4686 | E12: =Demanda!$D$31*Supuestos!$D31/Supuestos!$D$37 -> 1541.6687 | F12: =D12+E12 -> 2489.1373 | G12: =Demanda!C$16*Supuestos!$C31/Supuestos!$C$37/B12 -> 1.55684 | H12: =Demanda!D$16*Supuestos!$C31/Supuestos!$C$37/B12 -> 3.7898744 | I12: =Demanda!E$16*Supuestos!$C31/Supuestos!$C$37/B12 -> 8.8490636 | J12: =Demanda!C$31*Supuestos!$D31/Supuestos!$D$37/B12 -> 2.6248312 | K12: =Demanda!D$31*Supuestos!$D31/Supuestos!$D$37/B12 -> 6.1666747 | L12: =Demanda!E$31*Supuestos!$D31/Supuestos!$D$37/B12 -> 13.60716 | M12: =H12+K12 -> 9.9565491 | N12: =ROUNDUP(M12*(1+Supuestos!$C$19),0) -> 12 | O12: =ROUNDUP((I12+L12)*(1+Supuestos!$C$19),0) -> 26
A13: =Supuestos!A32 -> Sellos (madera, autoentintables y cera) | B13: =Supuestos!B32 -> 424 | C13: =Supuestos!E32 -> Bajo pedido | D13: =Demanda!$D$16*Supuestos!$C32/Supuestos!$C$37 -> 2368.6715 | E13: =Demanda!$D$31*Supuestos!$D32/Supuestos!$D$37 -> 1850.0024 | F13: =D13+E13 -> 4218.6739 | G13: =Demanda!C$16*Supuestos!$C32/Supuestos!$C$37/B13 -> 2.2948702 | H13: =Demanda!D$16*Supuestos!$C32/Supuestos!$C$37/B13 -> 5.5864894 | I13: =Demanda!E$16*Supuestos!$C32/Supuestos!$C$37/B13 -> 13.044021 | J13: =Demanda!C$31*Supuestos!$D32/Supuestos!$D$37/B13 -> 1.8571919 | K13: =Demanda!D$31*Supuestos!$D32/Supuestos!$D$37/B13 -> 4.3632132 | L13: =Demanda!E$31*Supuestos!$D32/Supuestos!$D$37/B13 -> 9.6277078 | M13: =H13+K13 -> 9.9497026 | N13: =ROUNDUP(M13*(1+Supuestos!$C$19),0) -> 12 | O13: =ROUNDUP((I13+L13)*(1+Supuestos!$C$19),0) -> 27
A14: =Supuestos!A33 -> Impresión 3D y otros personalizados | B14: =Supuestos!B33 -> 600 | C14: =Supuestos!E33 -> Bajo pedido | D14: =Demanda!$D$16*Supuestos!$C33/Supuestos!$C$37 -> 710.60145 | E14: =Demanda!$D$31*Supuestos!$D33/Supuestos!$D$37 -> 925.0012 | F14: =D14+E14 -> 1635.6026 | G14: =Demanda!C$16*Supuestos!$C33/Supuestos!$C$37/B14 -> 0.48651249 | H14: =Demanda!D$16*Supuestos!$C33/Supuestos!$C$37/B14 -> 1.1843357 | I14: =Demanda!E$16*Supuestos!$C33/Supuestos!$C$37/B14 -> 2.7653324 | J14: =Demanda!C$31*Supuestos!$D33/Supuestos!$D$37/B14 -> 0.65620779 | K14: =Demanda!D$31*Supuestos!$D33/Supuestos!$D$37/B14 -> 1.5416687 | L14: =Demanda!E$31*Supuestos!$D33/Supuestos!$D$37/B14 -> 3.4017901 | M14: =H14+K14 -> 2.7260044 | N14: =ROUNDUP(M14*(1+Supuestos!$C$19),0) -> 4 | O14: =ROUNDUP((I14+L14)*(1+Supuestos!$C$19),0) -> 8
A15: =Supuestos!A34 -> Mini CD con NFC | B15: =Supuestos!B34 -> 185 | C15: =Supuestos!E34 -> Stock | D15: =Demanda!$D$16*Supuestos!$C34/Supuestos!$C$37 -> 1421.2029 | E15: =Demanda!$D$31*Supuestos!$D34/Supuestos!$D$37 -> 2466.6699 | F15: =D15+E15 -> 3887.8728 | G15: =Demanda!C$16*Supuestos!$C34/Supuestos!$C$37/B15 -> 3.1557567 | H15: =Demanda!D$16*Supuestos!$C34/Supuestos!$C$37/B15 -> 7.6821778 | I15: =Demanda!E$16*Supuestos!$C34/Supuestos!$C$37/B15 -> 17.937291 | J15: =Demanda!C$31*Supuestos!$D34/Supuestos!$D$37/B15 -> 5.6753106 | K15: =Demanda!D$31*Supuestos!$D34/Supuestos!$D$37/B15 -> 13.333351 | L15: =Demanda!E$31*Supuestos!$D34/Supuestos!$D$37/B15 -> 29.420887 | M15: =H15+K15 -> 21.015528 | N15: =ROUNDUP(M15*(1+Supuestos!$C$19),0) -> 25 | O15: =ROUNDUP((I15+L15)*(1+Supuestos!$C$19),0) -> 55
A16: =Supuestos!A35 -> Colección Pride | B16: =Supuestos!B35 -> 269 | C16: =Supuestos!E35 -> Stock | D16: =Demanda!$D$16*Supuestos!$C35/Supuestos!$C$37 -> 710.60145 | E16: =Demanda!$D$31*Supuestos!$D35/Supuestos!$D$37 -> 616.66747 | F16: =D16+E16 -> 1327.2689 | G16: =Demanda!C$16*Supuestos!$C35/Supuestos!$C$37/B16 -> 1.085158 | H16: =Demanda!D$16*Supuestos!$C35/Supuestos!$C$37/B16 -> 2.6416411 | I16: =Demanda!E$16*Supuestos!$C35/Supuestos!$C$37/B16 -> 6.1680276 | J16: =Demanda!C$31*Supuestos!$D35/Supuestos!$D$37/B16 -> 0.97577367 | K16: =Demanda!D$31*Supuestos!$D35/Supuestos!$D$37/B16 -> 2.2924441 | L16: =Demanda!E$31*Supuestos!$D35/Supuestos!$D$37/B16 -> 5.0584239 | M16: =H16+K16 -> 4.9340852 | N16: =ROUNDUP(M16*(1+Supuestos!$C$19),0) -> 6 | O16: =ROUNDUP((I16+L16)*(1+Supuestos!$C$19),0) -> 13
A17: =Supuestos!A36 -> Kits y regalos de temporada (Navidad) | B17: =Supuestos!B36 -> 900 | C17: =Supuestos!E36 -> Bajo pedido | D17: =Demanda!$D$16*Supuestos!$C36/Supuestos!$C$37 -> 2368.6715 | E17: =Demanda!$D$31*Supuestos!$D36/Supuestos!$D$37 -> 3700.0048 | F17: =D17+E17 -> 6068.6763 | G17: =Demanda!C$16*Supuestos!$C36/Supuestos!$C$37/B17 -> 1.0811389 | H17: =Demanda!D$16*Supuestos!$C36/Supuestos!$C$37/B17 -> 2.6318572 | I17: =Demanda!E$16*Supuestos!$C36/Supuestos!$C$37/B17 -> 6.145183 | J17: =Demanda!C$31*Supuestos!$D36/Supuestos!$D$37/B17 -> 1.7498874 | K17: =Demanda!D$31*Supuestos!$D36/Supuestos!$D$37/B17 -> 4.1111164 | L17: =Demanda!E$31*Supuestos!$D36/Supuestos!$D$37/B17 -> 9.0714402 | M17: =H17+K17 -> 6.7429737 | N17: =ROUNDUP(M17*(1+Supuestos!$C$19),0) -> 8 | O17: =ROUNDUP((I17+L17)*(1+Supuestos!$C$19),0) -> 18
A18: TOTAL | D18: =SUM(D5:D17) -> 22265.512 | E18: =SUM(E5:E17) -> 30216.706 | F18: =SUM(F5:F17) -> 52482.218
A20: Piezas de ficha de lotería a imprimir (sueltas + dentro de paquetes)
A21: Escenario | D21: Piezas nov | E21: Piezas dic | F21: Piezas nov + dic | N21: Producir (+ colchón)
A22: Conservador | D22: =SUMPRODUCT(G5:G8,Supuestos!$G$24:$G$27) -> 1063.7377 | E22: =SUMPRODUCT(J5:J8,Supuestos!$G$24:$G$27) -> 1406.7845 | F22: =D22+E22 -> 2470.5222 | N22: =ROUNDUP(F22*(1+Supuestos!$C$19),0) -> 2842
A23: Base | D23: =SUMPRODUCT(H5:H8,Supuestos!$G$24:$G$27) -> 2589.4968 | E23: =SUMPRODUCT(K5:K8,Supuestos!$G$24:$G$27) -> 3305.044 | F23: =D23+E23 -> 5894.5408 | N23: =ROUNDUP(F23*(1+Supuestos!$C$19),0) -> 6779
A24: Optimista | D24: =SUMPRODUCT(I5:I8,Supuestos!$G$24:$G$27) -> 6046.2748 | E24: =SUMPRODUCT(L5:L8,Supuestos!$G$24:$G$27) -> 7292.79 | F24: =D24+E24 -> 13339.065 | N24: =ROUNDUP(F24*(1+Supuestos!$C$19),0) -> 15340
A26: Las piezas de ficha incluyen las de los paquetes: un paquete de 100 consume 100 fichas. Revisa tu capacidad de impresión 3D contra la fila Base antes de comprometer fechas.

Sheet Fuentes
A1: Fuentes consultadas (octubre de 2026)
A3: Dato | B3: Fuente
A4: Población de México 130.9 millones | B4: INEGI, Encuesta Intercensal 2025: https://www.unotv.com/nacional/mexico-suma-130-millones-habitantes-envejece-inegi/
A5: Gasto en regalos de Navidad $6,359 por hogar (Kantar) | B5: https://www.milenio.com/negocios/consumo-navideno-2025-mexicanos-gastaran-6-mil-360-pesos-regalos
A6: Otras estimaciones de gasto en regalos ($4,022 a $7,250) | B6: https://www.elfinanciero.com.mx/economia/2025/12/17/mexicanos-compran-regalos-de-navidad-2025-con-cautela-y-control-del-gasto/
A7: Parte de la Navidad que se compra en línea (21% a 55%, Deloitte) | B7: https://marketing4ecommerce.mx/ecommerce-gasto-navidad-mexico/
A8: Buen Fin 2025: derrama de $219 mil millones, +26.6% | B8: https://mexicobusiness.news/ecommerce/news/buen-fin-2025-sales-climb-266-e-commerce-accounts-21
A9: Buen Fin 2025: ventas en línea $45.9 mil millones (AMVO) | B9: https://marketing4ecommerce.mx/buen-fin-ventas-en-linea-mexico/
A10: Comercio electrónico 2025 y compradores digitales (AMVO) | B10: https://mexicoindustry.com/noticia/e-commerce-en-mexico-deja-casi-790-ml-mdp-en-ventas-amvo
A11: Ticket del Hot Sale 2025 | B11: https://expansion.mx/tecnologia/2025/07/08/hot-sale-2025-genero-mas-ventas-pero-gastaron-menos
A12: Precios de los productos | B12: Tienda Mosaicca (catálogo vigente al 29 de octubre de 2026).
A13: CPM, CTR, conversión, ticket, pedidos orgánicos, mezcla y factores de temporada | B13: Supuestos del modelo, sin fuente pública. Sustitúyelos con tus datos de Ads Manager y de tus pedidos.
